opisense_client/__init__.py
opisense_client/http.py
opisense_client/inputs.py
opisense_client/objects.py
opisense_client/tests/__init__.py
opisense_client/tests/tests.py
opisense_client-1.5.3.dist-info/LICENSE
opisense_client-1.5.3.dist-info/METADATA
opisense_client-1.5.3.dist-info/WHEEL
opisense_client-1.5.3.dist-info/top_level.txt
opisense_client-1.5.3.dist-info/RECORD
