Metadata-Version: 2.1
Name: opisense-client
Version: 1.5.3
Summary: Package to interact with the Opisense API
Home-page: https://github.com/opinum/opisense_client
Download-URL: https://github.com/opinum/opisense_client/archive/1.2.3.tar.gz
Author: Patrick Watteyne
Author-email: pwa@opinum.com
Classifier: Programming Language :: Python :: 3.6
Classifier: License :: OSI Approved :: MIT License
Classifier: Operating System :: OS Independent
License-File: LICENSE
Requires-Dist: requests
Requires-Dist: requests-oauthlib
Requires-Dist: oauthlib
